num_solver/__init__.py
num_solver/networks.py
num_solver/solver.py
num_solver/topology.py
num_solver/utility_functions.py
num_solver-0.1.9.dist-info/DESCRIPTION.rst
num_solver-0.1.9.dist-info/METADATA
num_solver-0.1.9.dist-info/RECORD
num_solver-0.1.9.dist-info/WHEEL
num_solver-0.1.9.dist-info/metadata.json
num_solver-0.1.9.dist-info/pbr.json
num_solver-0.1.9.dist-info/top_level.txt
